storyboard/__init__.py
storyboard/_i18n.py
storyboard/api/__init__.py
storyboard/api/app.py
storyboard/api/app.wsgi
storyboard/api/config.py
storyboard/api/root_controller.py
storyboard/api/auth/__init__.py
storyboard/api/auth/authorization_checks.py
storyboard/api/auth/oauth_validator.py
storyboard/api/auth/openid_client.py
storyboard/api/auth/utils.py
storyboard/api/middleware/__init__.py
storyboard/api/middleware/cors_middleware.py
storyboard/api/middleware/session_hook.py
storyboard/api/middleware/token_middleware.py
storyboard/api/middleware/user_id_hook.py
storyboard/api/middleware/validation_hook.py
storyboard/api/v1/__init__.py
storyboard/api/v1/attachments.py
storyboard/api/v1/auth.py
storyboard/api/v1/base.py
storyboard/api/v1/boards.py
storyboard/api/v1/branches.py
storyboard/api/v1/due_dates.py
storyboard/api/v1/milestones.py
storyboard/api/v1/project_groups.py
storyboard/api/v1/projects.py
storyboard/api/v1/stories.py
storyboard/api/v1/subscription_events.py
storyboard/api/v1/subscriptions.py
storyboard/api/v1/system_info.py
storyboard/api/v1/tags.py
storyboard/api/v1/task_statuses.py
storyboard/api/v1/tasks.py
storyboard/api/v1/teams.py
storyboard/api/v1/timeline.py
storyboard/api/v1/user_preferences.py
storyboard/api/v1/user_tokens.py
storyboard/api/v1/users.py
storyboard/api/v1/v1_controller.py
storyboard/api/v1/validations.py
storyboard/api/v1/wmodels.py
storyboard/api/v1/worklists.py
storyboard/api/v1/search/__init__.py
storyboard/api/v1/search/impls.py
storyboard/api/v1/search/search_engine.py
storyboard/api/v1/search/sqlalchemy_impl.py
storyboard/api/v1/storage/__init__.py
storyboard/api/v1/storage/impls.py
storyboard/api/v1/storage/storage.py
storyboard/api/v1/storage/swift_impl.py
storyboard/common/__init__.py
storyboard/common/custom_types.py
storyboard/common/decorators.py
storyboard/common/event_resolvers.py
storyboard/common/event_types.py
storyboard/common/exception.py
storyboard/common/hook_priorities.py
storyboard_api-1.1.0.dist-info/AUTHORS
storyboard_api-1.1.0.dist-info/LICENSE
storyboard_api-1.1.0.dist-info/METADATA
storyboard_api-1.1.0.dist-info/WHEEL
storyboard_api-1.1.0.dist-info/entry_points.txt
storyboard_api-1.1.0.dist-info/pbr.json
storyboard_api-1.1.0.dist-info/top_level.txt
storyboard_api-1.1.0.dist-info/RECORD
