Metadata-Version: 2.1
Name: storyboard-api
Version: 1.1.0
Summary: StoryBoard Task Tracker API Service
Home-page: https://docs.openstack.org/infra/storyboard
Author: OpenDev
Author-email: openstack-discuss@lists.openstack.org
License: UNKNOWN
Project-URL: Browse Source, https://opendev.org/opendev/storyboard
Project-URL: Bug Reporting, https://storyboard.openstack.org/#!/project/opendev/storyboard
Project-URL: Documentation, https://docs.openstack.org/infra/storyboard
Project-URL: Git Clone URL, https://opendev.org/opendev/storyboard
Platform: UNKNOWN
Classifier: Environment :: Web Environment
Classifier: Intended Audience :: Developers
Classifier: Intended Audience :: Information Technology
Classifier: Intended Audience :: System Administrators
Classifier: License :: OSI Approved :: Apache Software License
Classifier: Operating System :: OS Independent
Classifier: Operating System :: POSIX :: Linux
Classifier: Programming Language :: Python
Classifier: Programming Language :: Python :: 2.7
Classifier: Programming Language :: Python :: 3
Classifier: Programming Language :: Python :: 3.5
Classifier: Topic :: Software Development :: Bug Tracking
Requires-Dist: pbr (>=5)
Requires-Dist: jsonschema (<3.0.0,>=2.0.0)
Requires-Dist: alembic (>=0.4.1)
Requires-Dist: Babel (>=1.3)
Requires-Dist: iso8601 (>=0.1.9)
Requires-Dist: oauthlib (<3,>=0.6)
Requires-Dist: oslo.config (>=1.11.0)
Requires-Dist: oslo.context (>=0.2.0)
Requires-Dist: oslo.utils (>=1.4.0)
Requires-Dist: pecan (>=0.4.5)
Requires-Dist: oslo.db (>=4.27.0)
Requires-Dist: oslo.log (>=1.0.0)
Requires-Dist: pika (>=0.9.14)
Requires-Dist: PyYAML (>=3.1.0)
Requires-Dist: requests (>=1.1)
Requires-Dist: six (>=1.7.0)
Requires-Dist: SQLAlchemy
Requires-Dist: webob (==1.7.4)
Requires-Dist: WSME (<0.8,>=0.6)
Requires-Dist: SQLAlchemy-FullText-Search (>=0.2.3)
Requires-Dist: stevedore (>=1.3.0)
Requires-Dist: tzlocal (>=1.1.2)
Requires-Dist: Jinja2 (>=2.7.3)
Requires-Dist: PyMySQL (!=0.6.4,>=0.6.2)
Requires-Dist: apscheduler (<3.1.0,>=3.0.1)
Requires-Dist: python-dateutil (>=2.4.0)
Requires-Dist: oslo.concurrency (>=3.8.0)
Requires-Dist: oslo.i18n (>=2.1.0)
Requires-Dist: python-swiftclient
Requires-Dist: openstacksdk
Requires-Dist: python-openid ; (python_version < '3.0')
Requires-Dist: python3-openid ; (python_version >= '3.0')
Requires-Dist: email (>=4.0.2) ; (python_version<'3.0')
